pos.v
module receiver #(
    parameter DW_IN = 64
) 
(
    input clk,
    input [DW_IN - 1:0] data,
    output reg [7:0] pos = 0
);

reg unsigned [7:0] i = 0;
reg unsigned [7:0] buff[63:0];

wire [7:0] b0 = buff[0];
wire [7:0] b1 = buff[1];
wire [7:0] b2 = buff[2];
wire [7:0] b3 = buff[3];
wire [7:0] b4 = buff[4];
wire [7:0] b5 = buff[5];
wire [7:0] b6 = buff[6];
wire [7:0] b7 = buff[7];


always @(posedge clk) 
begin
    for (i=0; i<8; i=i+1)
    begin
        if (data[8*i + 7])
            buff[i] <= 8;
        else if (data[8*i + 6])
            buff[i] <= 7;
        else if (data[8*i + 5])
            buff[i] <= 6;
        else if (data[8*i + 4])
            buff[i] <= 5;
        else if (data[8*i + 3])
            buff[i] <= 4;
        else if (data[8*i + 2])
            buff[i] <= 3;
        else if (data[8*i + 1])
            buff[i] <= 2;
        else if (data[8*i + 0])
            buff[i] <= 1;
        else
            buff[i] <= 0;
    end

    pos <= 0;
    if(buff[7])
        pos <= buff[7] + 56;
    else if (buff[6])
        pos <= buff[6] + 48;
    else if (buff[5])
        pos <= buff[5] + 40;
    else if (buff[4])
        pos <= buff[4] + 32;
    else if (buff[3])
        pos <= buff[3] + 24;
    else if (buff[2])
        pos <= buff[2] + 16;
    else if (buff[1])
        pos <= buff[1] + 8;
    else if (buff[0])
        pos <= buff[0];
    else
        pos <= 0;

end


endmodule

tb.v
module tb;
    parameter DW_IN = 512;
    reg clk = 0;
    reg [DW_IN - 1:0] data = 'h753;

    initial
    begin
        #1000 $finish;
    end

    initial
    begin
        forever #25 clk = ~clk;
    end

    initial
    begin
        while(1)
        begin
            data = 'h123;
            #50;
            data = 'h456;
            #50;
            data = 'h789;
            #50;
        end
    end

    initial
    begin
        $dumpfile("dump.vcd");
        $dumpvars(0, tb);
    end

    receiver #( .DW_IN(DW_IN) ) 
    rec0 (
        .clk(clk),
        .data(data)
    );

endmodule

dump.vcd
$date
	Tue Dec 13 17:59:08 2022
$end
$version
	Icarus Verilog
$end
$timescale
	1s
$end
$scope module tb $end
$var parameter 32 ! DW_IN $end
$var reg 1 " clk $end
$var reg 64 # data [63:0] $end
$scope module rec0 $end
$var wire 8 $ b0 [7:0] $end
$var wire 8 % b1 [7:0] $end
$var wire 8 & b2 [7:0] $end
$var wire 8 ' b3 [7:0] $end
$var wire 8 ( b4 [7:0] $end
$var wire 8 ) b5 [7:0] $end
$var wire 8 * b6 [7:0] $end
$var wire 8 + b7 [7:0] $end
$var wire 1 " clk $end
$var wire 64 , data [63:0] $end
$var parameter 32 - DW_IN $end
$var reg 8 . i [7:0] $end
$var reg 8 / pos [7:0] $end
$upscope $end
$upscope $end
$enddefinitions $end
$comment Show the parameter values. $end
$dumpall
b1000000 -
b1000000 !
$end
#0
$dumpvars
b0 /
b0 .
b100100011 ,
bx +
bx *
bx )
bx (
bx '
bx &
bx %
bx $
b100100011 #
0"
$end
#25
b0 +
b0 *
b0 )
b0 (
b0 '
b0 &
b1 %
b110 $
b1000 .
1"
#50
0"
b10001010110 #
b10001010110 ,
#75
b1001 /
b11 %
b111 $
b1000 .
1"
#100
0"
b11110001001 #
b11110001001 ,
#125
b1011 /
b1000 $
b1000 .
1"
#150
0"
b100100011 #
b100100011 ,
#175
b1011 /
b1 %
b110 $
b1000 .
1"
#200
0"
b10001010110 #
b10001010110 ,
#225
b1001 /
b11 %
b111 $
b1000 .
1"
#250
0"
b11110001001 #
b11110001001 ,
#275
b1011 /
b1000 $
b1000 .
1"
#300
0"
b100100011 #
b100100011 ,
#325
b1011 /
b1 %
b110 $
b1000 .
1"
#350
0"
b10001010110 #
b10001010110 ,
#375
b1001 /
b11 %
b111 $
b1000 .
1"
#400
0"
b11110001001 #
b11110001001 ,
#425
b1011 /
b1000 $
b1000 .
1"
#450
0"
b100100011 #
b100100011 ,
#475
b1011 /
b1 %
b110 $
b1000 .
1"
#500
0"
b10001010110 #
b10001010110 ,
#525
b1001 /
b11 %
b111 $
b1000 .
1"
#550
0"
b11110001001 #
b11110001001 ,
#575
b1011 /
b1000 $
b1000 .
1"
#600
0"
b100100011 #
b100100011 ,
#625
b1011 /
b1 %
b110 $
b1000 .
1"
#650
0"
b10001010110 #
b10001010110 ,
#675
b1001 /
b11 %
b111 $
b1000 .
1"
#700
0"
b11110001001 #
b11110001001 ,
#725
b1011 /
b1000 $
b1000 .
1"
#750
0"
b100100011 #
b100100011 ,
#775
b1011 /
b1 %
b110 $
b1000 .
1"
#800
0"
b10001010110 #
b10001010110 ,
#825
b1001 /
b11 %
b111 $
b1000 .
1"
#850
0"
b11110001001 #
b11110001001 ,
#875
b1011 /
b1000 $
b1000 .
1"
#900
0"
b100100011 #
b100100011 ,
#925
b1011 /
b1 %
b110 $
b1000 .
1"
#950
0"
b10001010110 #
b10001010110 ,
#975
b1001 /
b11 %
b111 $
b1000 .
1"
#1000
0"
b11110001001 #
b11110001001 ,
